imgaug/DejaVuSans.ttf
imgaug/__init__.py
imgaug/data.py
imgaug/dtypes.py
imgaug/imgaug.py
imgaug/multicore.py
imgaug/parameters.py
imgaug/quokka.jpg
imgaug/quokka_annotations.json
imgaug/quokka_depth_map_halfres.png
imgaug/random.py
imgaug/testutils.py
imgaug/validation.py
imgaug/augmentables/__init__.py
imgaug/augmentables/base.py
imgaug/augmentables/batches.py
imgaug/augmentables/bbs.py
imgaug/augmentables/heatmaps.py
imgaug/augmentables/kps.py
imgaug/augmentables/lines.py
imgaug/augmentables/normalization.py
imgaug/augmentables/polys.py
imgaug/augmentables/segmaps.py
imgaug/augmentables/utils.py
imgaug/augmenters/__init__.py
imgaug/augmenters/arithmetic.py
imgaug/augmenters/artistic.py
imgaug/augmenters/base.py
imgaug/augmenters/blend.py
imgaug/augmenters/blur.py
imgaug/augmenters/collections.py
imgaug/augmenters/color.py
imgaug/augmenters/contrast.py
imgaug/augmenters/convolutional.py
imgaug/augmenters/debug.py
imgaug/augmenters/edges.py
imgaug/augmenters/flip.py
imgaug/augmenters/geometric.py
imgaug/augmenters/imgcorruptlike.py
imgaug/augmenters/meta.py
imgaug/augmenters/overlay.py
imgaug/augmenters/pillike.py
imgaug/augmenters/pooling.py
imgaug/augmenters/segmentation.py
imgaug/augmenters/size.py
imgaug/augmenters/weather.py
imgaug/external/README.md
imgaug/external/__init__.py
imgaug/external/opensimplex.py
imgaug/external/poly_point_isect_py2py3.py
imgaug_denk-0.4.6.dist-info/LICENSE
imgaug_denk-0.4.6.dist-info/METADATA
imgaug_denk-0.4.6.dist-info/WHEEL
imgaug_denk-0.4.6.dist-info/top_level.txt
imgaug_denk-0.4.6.dist-info/RECORD
